denpy/__init__.py
denpy/color.py
denpy/database.py
denpy/utils.py
denpy-1.2.6.dist-info/METADATA
denpy-1.2.6.dist-info/WHEEL
denpy-1.2.6.dist-info/top_level.txt
denpy-1.2.6.dist-info/RECORD
