Metadata-Version: 2.1
Name: denpy
Version: 1.2.6
Summary: My own package!
Author: denflash
